{
  "$schema": "./node_modules/@openapitools/openapi-generator-cli/config.schema.json",
  "spaces": 2,
  "generator-cli": {
    "version": "7.6.0",
    "generators": {
      "sso-client": {
        "generatorName": "typescript-axios",
        "inputSpec": "libs/clients/src/sso-client/src/utils/oas.yml",
        "output": "libs/clients/src/sso-client/src/client/generated",
        "additionalProperties": {
          "stringEnums": true,
          "supportsES6": true,
          "typescriptThreePlus": true,
          "enumPropertyNaming": "original",
          "useSingleRequestParameter": true,
          "withNodeImports": true
        }
      }
    }
  }
}
